EcoStock/__init__.py
EcoStock/adalo.py
EcoStock/api.py
EcoStock/functions.py
ecostock-1.5.dist-info/licenses/LICENSE.md
ecostock-1.5.dist-info/METADATA
ecostock-1.5.dist-info/WHEEL
ecostock-1.5.dist-info/top_level.txt
ecostock-1.5.dist-info/RECORD
