Metadata-Version: 2.4
Name: EcoStock
Version: 1.5
Summary: A Python package designed for finance professionals and economists
Home-page: https://github.com/Tonij10/EcoStock
Author: Antonio Paparo, Giovanni Paparo
Author-email: antoniopaparo@outlook.com
Classifier: Programming Language :: Python :: 3
Classifier: License :: OSI Approved :: MIT License
Classifier: Operating System :: OS Independent
Requires-Python: >=3.10
License-File: LICENSE.md
Requires-Dist: fastapi
Requires-Dist: argparse
Requires-Dist: uvicorn
Requires-Dist: gunicorn
Requires-Dist: pandas
Requires-Dist: numpy
Requires-Dist: matplotlib
Requires-Dist: yfinance
Requires-Dist: plotly
Requires-Dist: requests
Requires-Dist: seaborn
Requires-Dist: statsmodels
Requires-Dist: nbformat
Requires-Dist: scikit-learn
Dynamic: author
Dynamic: author-email
Dynamic: classifier
Dynamic: description
Dynamic: description-content-type
Dynamic: home-page
Dynamic: license-file
Dynamic: requires-dist
Dynamic: requires-python
Dynamic: summary
